dradis/__init__.py
dradis/test.py
dradis_client-1.0.0.dist-info/LICENSE
dradis_client-1.0.0.dist-info/METADATA
dradis_client-1.0.0.dist-info/WHEEL
dradis_client-1.0.0.dist-info/top_level.txt
dradis_client-1.0.0.dist-info/RECORD
