Metadata-Version: 2.1
Name: dradis-client
Version: 1.0.0
Summary: Updated version of pydradis3 that was developed by GoVanguard
Home-page: https://github.com/no-sec-marko/dradis-client
Author: Marko Winkler
Author-email: mwinkler@omgwtfquak.de
License: UNKNOWN
Platform: UNKNOWN
Classifier: Development Status :: 3 - Alpha
Classifier: Intended Audience :: Developers
Classifier: License :: OSI Approved :: GNU General Public License v2 (GPLv2)
Classifier: Programming Language :: Python :: 3.6
Classifier: Operating System :: OS Independent
License-File: LICENSE
